MANIFEST.in
README.md
setup.cfg
setup.py
test.py
.lib/easy_install.py
.lib/about/Trove-classifiers.txt
.lib/about/__init__.py
.lib/about/about.py
.lib/about-5.2.egg-info/PKG-INFO
.lib/about-5.2.egg-info/SOURCES.txt
.lib/about-5.2.egg-info/dependency_links.txt
.lib/about-5.2.egg-info/installed-files.txt
.lib/about-5.2.egg-info/pbr.json
.lib/about-5.2.egg-info/requires.txt
.lib/about-5.2.egg-info/top_level.txt
.lib/pkg_resources/__init__.py
.lib/pkg_resources/_vendor/__init__.py
.lib/pkg_resources/_vendor/pyparsing.py
.lib/pkg_resources/_vendor/six.py
.lib/pkg_resources/_vendor/packaging/__about__.py
.lib/pkg_resources/_vendor/packaging/__init__.py
.lib/pkg_resources/_vendor/packaging/_compat.py
.lib/pkg_resources/_vendor/packaging/_structures.py
.lib/pkg_resources/_vendor/packaging/markers.py
.lib/pkg_resources/_vendor/packaging/requirements.py
.lib/pkg_resources/_vendor/packaging/specifiers.py
.lib/pkg_resources/_vendor/packaging/utils.py
.lib/pkg_resources/_vendor/packaging/version.py
.lib/pkg_resources/extern/__init__.py
.lib/setuptools/__init__.py
.lib/setuptools/archive_util.py
.lib/setuptools/cli-32.exe
.lib/setuptools/cli-64.exe
.lib/setuptools/cli.exe
.lib/setuptools/depends.py
.lib/setuptools/dist.py
.lib/setuptools/extension.py
.lib/setuptools/gui-32.exe
.lib/setuptools/gui-64.exe
.lib/setuptools/gui.exe
.lib/setuptools/launch.py
.lib/setuptools/lib2to3_ex.py
.lib/setuptools/msvc.py
.lib/setuptools/package_index.py
.lib/setuptools/py26compat.py
.lib/setuptools/py27compat.py
.lib/setuptools/py31compat.py
.lib/setuptools/sandbox.py
.lib/setuptools/script (dev).tmpl
.lib/setuptools/script.tmpl
.lib/setuptools/site-patch.py
.lib/setuptools/ssl_support.py
.lib/setuptools/unicode_utils.py
.lib/setuptools/utils.py
.lib/setuptools/version.py
.lib/setuptools/windows_support.py
.lib/setuptools-24.0.1.dist-info/DESCRIPTION.rst
.lib/setuptools-24.0.1.dist-info/METADATA
.lib/setuptools-24.0.1.dist-info/RECORD
.lib/setuptools-24.0.1.dist-info/WHEEL
.lib/setuptools-24.0.1.dist-info/dependency_links.txt
.lib/setuptools-24.0.1.dist-info/entry_points.txt
.lib/setuptools-24.0.1.dist-info/metadata.json
.lib/setuptools-24.0.1.dist-info/top_level.txt
.lib/setuptools-24.0.1.dist-info/zip-safe
.lib/setuptools/command/__init__.py
.lib/setuptools/command/alias.py
.lib/setuptools/command/bdist_egg.py
.lib/setuptools/command/bdist_rpm.py
.lib/setuptools/command/bdist_wininst.py
.lib/setuptools/command/build_ext.py
.lib/setuptools/command/build_py.py
.lib/setuptools/command/develop.py
.lib/setuptools/command/easy_install.py
.lib/setuptools/command/egg_info.py
.lib/setuptools/command/install.py
.lib/setuptools/command/install_egg_info.py
numtest.egg-info/PKG-INFO
numtest.egg-info/SOURCES.txt
numtest.egg-info/dependency_links.txt
numtest.egg-info/pbr.json
numtest.egg-info/requires.txt
numtest.egg-info/top_level.txt