Metadata-Version: 1.0
Name: numtest
Version: 2.0.4
Summary: Numeric Doctest
Home-page: https://github.com/boisgera/numtest
Author: Sébastien Boisgérault
Author-email: Sebastien.Boisgerault@mines-paristech.fr
License: MIT License
Platform: UNKNOWN
